{
  "feedback": [
    {
      "id": 1,
      "rating": 10,
      "text": "This is feedback item 1, coming from the backend"
    },
    {
      "id": 2,
      "rating": 7,
      "text": "This is feedback item 2, coming from the backend"
    },
    {
      "id": 31,
      "rating": 8,
      "text": "This is feedback item 3, coming from the backend"
    },
    {
      "id": 4,
      "rating": 9,
      "text": "This is feedback item 4, coming from the backend"
    },
    {
      "text": "This is an add Feedback test",
      "rating": 5,
      "id": 32
    }
  ]
}